{"input": {"Dso": {"value": 110.09422211129758, "unit": "mm"}, "Dsi": {"value": 61.6635781873881, "unit": "mm"}, "length": {"value": 93.63100454675892, "unit": "mm"}, "airgap": {"value": 0.46185613843557005, "unit": "mm"}, "mag_thick": {"value": 3.185554991967113, "unit": "mm"}, "mag_emb": {"value": 0.7964288602664684, "unit": "mm"}, "Wy": {"value": 5.841688434304471, "unit": "mm"}, "Wt": {"value": 9.592049537914164, "unit": "mm"}, "Hs0": {"value": 0.9133165269791059, "unit": "mm"}, "Hs1": {"value": 0.9933152874628997, "unit": "mm"}, "Bs0": {"value": 4.916290470836922, "unit": "mm"}, "slot": {"value": 13, "unit": ""}, "Im": {"value": 278.27528827819054, "unit": "A"}, "speed_rpm": {"value": 1703.6436479516321, "unit": "rpm"}}, "output": {"intersect": "YES"}}