{"input": {"Dso": {"value": 98.87119613277454, "unit": "mm"}, "Dsi": {"value": 55.478560053819834, "unit": "mm"}, "length": {"value": 105.51676608882804, "unit": "mm"}, "airgap": {"value": 0.46911299410242335, "unit": "mm"}, "mag_thick": {"value": 3.0282186292619078, "unit": "mm"}, "mag_emb": {"value": 0.7862937141082906, "unit": "mm"}, "Wy": {"value": 7.032392692761429, "unit": "mm"}, "Wt": {"value": 8.742272383500625, "unit": "mm"}, "Hs0": {"value": 0.9183880664332554, "unit": "mm"}, "Hs1": {"value": 1.0369077794457622, "unit": "mm"}, "Bs0": {"value": 4.437983617655357, "unit": "mm"}, "slot": {"value": 11, "unit": ""}, "Im": {"value": 270.52970855329386, "unit": "A"}, "speed_rpm": {"value": 1706.8860136377273, "unit": "rpm"}}, "output": {"intersect": "YES"}}