{"input": {"Dso": {"value": 102.067035570365, "unit": "mm"}, "Dsi": {"value": 62.23314649424454, "unit": "mm"}, "length": {"value": 99.14965939132968, "unit": "mm"}, "airgap": {"value": 0.4913577820015129, "unit": "mm"}, "mag_thick": {"value": 2.8306302903206677, "unit": "mm"}, "mag_emb": {"value": 0.7383333835567224, "unit": "mm"}, "Wy": {"value": 6.378379736671813, "unit": "mm"}, "Wt": {"value": 8.56585856081969, "unit": "mm"}, "Hs0": {"value": 0.9301047657450892, "unit": "mm"}, "Hs1": {"value": 0.998149492477164, "unit": "mm"}, "Bs0": {"value": 4.447312086847983, "unit": "mm"}, "slot": {"value": 10, "unit": ""}, "Im": {"value": 311.31266515071866, "unit": "A"}, "speed_rpm": {"value": 1700.0000725802001, "unit": "rpm"}}, "output": {"intersect": "YES"}}